{
    "task_location": 19,
    "task_level": 2,
    "task_type": "normal",
    "requires": {
        "0": [
            "any"
        ]
    },
    "0": {
        "initial_teams": [
            {
                "name": "A",
                "type": "blue",
                "position": "up"
            },
            {
                "name": "B",
                "type": "yellow",
                "position": "down"
            }
        ],
        "fight_plan": [
            [
                {
                    "team": "A",
                    "action": "move",
                    "target": "left-up"
                },
                {
                    "team": "B",
                    "action": "move",
                    "target": "right-up"
                }
            ],
            [
                {
                    "team": "A",
                    "action": "move",
                    "target": "left-up"
                },
                {
                    "team": "B",
                    "action": "move",
                    "target": "right-up"
                }
            ],
            [
                {
                    "team": "A",
                    "action": "move",
                    "target": "right"
                },
                {
                    "team": "B",
                    "action": "move",
                    "target": "right-up"
                }
            ],
            [
                {
                    "team": "A",
                    "action": "move",
                    "target": "left-up"
                },
                {
                    "team": "B",
                    "action": "move",
                    "target": "right-up"
                }
            ]
        ]
    }
}