{
    "task_location": 5,
    "task_level": 2,
    "task_type": "hard",
    "requires": {
        "0": [
            "any"
        ]
    },
    "0": {
        "initial_teams": [
            {
                "name": "A",
                "type": "any",
                "position": "center"
            }
        ],
        "fight_plan": [
            [
                {
                    "team": "A",
                    "action": "move",
                    "target": "right"
                }
            ],
            [
                {
                    "team": "A",
                    "action": "move",
                    "target": "right-down"
                }
            ],
            [
                {
                    "team": "A",
                    "action": "move",
                    "target": "right"
                }
            ],
            [
                {
                    "team": "A",
                    "action": "move",
                    "target": "right-up"
                }
            ]
        ]
    }
}